{"meta": {"engine_version": "5.1", "computed_at": "2026-01-01T00:00:00", "profile_fidelity": "FULL_METRIC", "time_context": {"local": "1990-05-15T14:30:00+05:30", "utc": "1990-05-15T09:00:00+00:00", "jdn_ut": 2448026.875, "jd_lmt": 2448027.09301861, "lst_hours": 5.754645, "timezone": "Asia/Kolkata", "time_known": true}}, "profile_fidelity": "FULL_METRIC", "vedic": {"ascendant": {"total_degrees": 152.7428, "sign": "Virgo", "degrees_in_sign": 2.7428, "dms": "2\u00b044'34.0\"", "nakshatra": "Uttara Phalguni", "nakshatra_pada": 2, "nakshatra_lord": "Sun"}, "midheaven": {"total_degrees": 62.8969, "sign": "Gemini", "degrees_in_sign": 2.8969}, "planets": {"Sun": {"total_degrees": 30.5498, "sign": "Taurus", "degrees_in_sign": 0.5498, "dms": "0\u00b032'59.2\"", "retrograde": false, "speed_deg_day": 0.9642, "nakshatra": "Krittika", "nakshatra_pada": 2, "nakshatra_lord": "Sun", "percent_through_nakshatra": 29.1, "is_gandanta": false, "is_nakshatra_gandanta": false, "house_whole_sign": 9}, "Moon": {"total_degrees": 271.8935, "sign": "Capricorn", "degrees_in_sign": 1.8935, "dms": "1\u00b053'36.8\"", "retrograde": false, "speed_deg_day": 12.326, "nakshatra": "Uttara Ashadha", "nakshatra_pada": 2, "nakshatra_lord": "Sun", "percent_through_nakshatra": 39.2, "is_gandanta": false, "is_nakshatra_gandanta": false, "house_whole_sign": 5}, "Mars": {"total_degrees": 324.5152, "sign": "Aquarius", "degrees_in_sign": 24.5152, "dms": "24\u00b030'54.8\"", "retrograde": false, "speed_deg_day": 0.7427, "nakshatra": "Purva Bhadrapada", "nakshatra_pada": 2, "nakshatra_lord": "Jupiter", "percent_through_nakshatra": 33.9, "is_gandanta": false, "is_nakshatra_gandanta": false, "house_whole_sign": 6}, "Mercury": {"total_degrees": 14.3023, "sign": "Aries", "degrees_in_sign": 14.3023, "dms": "14\u00b018'8.2\"", "retrograde": true, "speed_deg_day": -0.1298, "nakshatra": "Bharani", "nakshatra_pada": 1, "nakshatra_lord": "Venus", "percent_through_nakshatra": 7.3, "is_gandanta": false, "is_nakshatra_gandanta": false, "house_whole_sign": 8}, "Jupiter": {"total_degrees": 75.7923, "sign": "Gemini", "degrees_in_sign": 15.7923, "dms": "15\u00b047'32.1\"", "retrograde": false, "speed_deg_day": 0.189, "nakshatra": "Ardra", "nakshatra_pada": 3, "nakshatra_lord": "Rahu", "percent_through_nakshatra": 68.4, "is_gandanta": false, "is_nakshatra_gandanta": false, "house_whole_sign": 10}, "Venus": {"total_degrees": 348.9499, "sign": "Pisces", "degrees_in_sign": 18.9499, "dms": "18\u00b056'59.8\"", "retrograde": false, "speed_deg_day": 1.1404, "nakshatra": "Revati", "nakshatra_pada": 1, "nakshatra_lord": "Mercury", "percent_through_nakshatra": 17.1, "is_gandanta": false, "is_nakshatra_gandanta": false, "house_whole_sign": 7}, "Saturn": {"total_degrees": 271.5257, "sign": "Capricorn", "degrees_in_sign": 1.5257, "dms": "1\u00b031'32.7\"", "retrograde": true, "speed_deg_day": -0.0168, "nakshatra": "Uttara Ashadha", "nakshatra_pada": 2, "nakshatra_lord": "Sun", "percent_through_nakshatra": 36.4, "is_gandanta": false, "is_nakshatra_gandanta": false, "house_whole_sign": 5}, "Rahu": {"total_degrees": 287.62, "sign": "Capricorn", "degrees_in_sign": 17.62, "dms": "17\u00b037'11.9\"", "retrograde": true, "speed_deg_day": -0.053, "nakshatra": "Shravana", "nakshatra_pada": 3, "nakshatra_lord": "Moon", "percent_through_nakshatra": 57.1, "is_gandanta": false, "is_nakshatra_gandanta": false, "true_node_degrees": 286.53, "true_node_deg_in_sign": 16.53, "house_whole_sign": 5}, "Ketu": {"total_degrees": 107.62, "sign": "Cancer", "degrees_in_sign": 17.62, "dms": "17\u00b037'12.0\"", "retrograde": true, "speed_deg_day": 0.053, "nakshatra": "Ashlesha", "nakshatra_pada": 1, "nakshatra_lord": "Mercury", "percent_through_nakshatra": 7.1, "is_gandanta": false, "is_nakshatra_gandanta": false, "house_whole_sign": 11}}, "functional_nature": {"Sun": {"houses_owned": [12], "functional_nature": "Malefic", "reason": "owns [12] for Virgo Lagna"}, "Moon": {"houses_owned": [11], "functional_nature": "Mixed", "reason": "owns [11] for Virgo Lagna"}, "Mars": {"houses_owned": [3, 8], "functional_nature": "Mixed", "reason": "owns [3, 8] for Virgo Lagna"}, "Mercury": {"houses_owned": [1, 10], "functional_nature": "Yogakaraka", "reason": "owns both a kendra and a trikona ([1, 10])"}, "Jupiter": {"houses_owned": [4, 7], "functional_nature": "Maraka", "reason": "owns [4, 7] for Virgo Lagna"}, "Venus": {"houses_owned": [2, 9], "functional_nature": "Maraka", "reason": "owns [2, 9] for Virgo Lagna"}, "Saturn": {"houses_owned": [5, 6], "functional_nature": "Mixed", "reason": "owns [5, 6] for Virgo Lagna"}}, "dignities": {"Sun": {"essential_dignity": "Neutral", "accidental_dignity": "Cadent", "kendradi_bala": "low", "vargottama": false, "combust": false, "baladi_avastha": "Mrita (dead \u2014 nil)", "dignity_boundary_flag": false, "kshudita": false, "mudita": false, "sign_lord": "Venus", "exaltation_dispositor": "Mars"}, "Moon": {"essential_dignity": "Neutral", "accidental_dignity": "Succedent", "kendradi_bala": "medium", "vargottama": true, "combust": false, "baladi_avastha": "Mrita (dead \u2014 nil)", "dignity_boundary_flag": false, "kshudita": false, "mudita": false, "sign_lord": "Saturn", "exaltation_dispositor": "Venus"}, "Mars": {"essential_dignity": "Neutral", "accidental_dignity": "Cadent", "kendradi_bala": "low", "vargottama": false, "combust": false, "baladi_avastha": "Mrita (dead \u2014 nil)", "dignity_boundary_flag": false, "kshudita": false, "mudita": false, "sign_lord": "Saturn", "exaltation_dispositor": "Saturn"}, "Mercury": {"essential_dignity": "Neutral", "accidental_dignity": "Succedent", "kendradi_bala": "medium", "vargottama": false, "combust": false, "baladi_avastha": "Yuva (youth \u2014 peak strength)", "dignity_boundary_flag": false, "kshudita": false, "mudita": false, "sign_lord": "Mars", "exaltation_dispositor": "Mercury"}, "Jupiter": {"essential_dignity": "Neutral", "accidental_dignity": "Angular", "kendradi_bala": "high", "vargottama": false, "combust": false, "baladi_avastha": "Yuva (youth \u2014 peak strength)", "dignity_boundary_flag": false, "kshudita": false, "mudita": false, "sign_lord": "Mercury", "exaltation_dispositor": "Moon"}, "Venus": {"essential_dignity": "Exalted", "accidental_dignity": "Angular", "kendradi_bala": "high", "vargottama": false, "combust": false, "baladi_avastha": "Kumara (child \u2014 growing)", "dignity_boundary_flag": false, "kshudita": false, "mudita": false, "sign_lord": "Jupiter", "exaltation_dispositor": "Jupiter"}, "Saturn": {"essential_dignity": "Own", "accidental_dignity": "Succedent", "kendradi_bala": "medium", "vargottama": true, "combust": false, "baladi_avastha": "Mrita (dead \u2014 nil)", "dignity_boundary_flag": false, "kshudita": false, "mudita": false, "sign_lord": "Saturn", "exaltation_dispositor": "Venus"}, "Rahu": {"essential_dignity": "Neutral", "accidental_dignity": "Succedent", "kendradi_bala": "medium", "vargottama": false, "combust": false, "baladi_avastha": "Yuva (youth \u2014 peak strength)", "dignity_boundary_flag": false, "kshudita": false, "mudita": false, "sign_lord": "Saturn", "exaltation_dispositor": "Venus"}, "Ketu": {"essential_dignity": "Neutral", "accidental_dignity": "Succedent", "kendradi_bala": "medium", "vargottama": false, "combust": false, "baladi_avastha": "Yuva (youth \u2014 peak strength)", "dignity_boundary_flag": false, "kshudita": false, "mudita": false, "sign_lord": "Moon", "exaltation_dispositor": "Mars"}}, "divisional_charts": {"D1": {"available": true, "lagna_sign": "Virgo", "planets": {"Sun": "Taurus", "Moon": "Capricorn", "Mars": "Aquarius", "Mercury": "Aries", "Jupiter": "Gemini", "Venus": "Pisces", "Saturn": "Capricorn", "Rahu": "Capricorn", "Ketu": "Cancer"}}, "D2": {"available": true, "lagna_sign": "Cancer", "planets": {"Sun": "Cancer", "Moon": "Cancer", "Mars": "Cancer", "Mercury": "Leo", "Jupiter": "Cancer", "Venus": "Leo", "Saturn": "Cancer", "Rahu": "Leo", "Ketu": "Leo"}}, "D3": {"available": true, "lagna_sign": "Virgo", "planets": {"Sun": "Taurus", "Moon": "Capricorn", "Mars": "Libra", "Mercury": "Leo", "Jupiter": "Libra", "Venus": "Cancer", "Saturn": "Capricorn", "Rahu": "Taurus", "Ketu": "Scorpio"}}, "D4": {"available": true, "lagna_sign": "Virgo", "planets": {"Sun": "Taurus", "Moon": "Capricorn", "Mars": "Scorpio", "Mercury": "Cancer", "Jupiter": "Sagittarius", "Venus": "Virgo", "Saturn": "Capricorn", "Rahu": "Cancer", "Ketu": "Capricorn"}}, "D5": {"available": true, "lagna_sign": "Virgo", "planets": {"Sun": "Taurus", "Moon": "Capricorn", "Mars": "Gemini", "Mercury": "Gemini", "Jupiter": "Leo", "Venus": "Gemini", "Saturn": "Capricorn", "Rahu": "Pisces", "Ketu": "Virgo"}}, "D6": {"available": true, "lagna_sign": "Virgo", "planets": {"Sun": "Taurus", "Moon": "Capricorn", "Mars": "Gemini", "Mercury": "Gemini", "Jupiter": "Virgo", "Venus": "Gemini", "Saturn": "Capricorn", "Rahu": "Aries", "Ketu": "Libra"}}, "D7": {"available": true, "lagna_sign": "Pisces", "planets": {"Sun": "Scorpio", "Moon": "Cancer", "Mars": "Cancer", "Mercury": "Cancer", "Jupiter": "Virgo", "Venus": "Capricorn", "Saturn": "Cancer", "Rahu": "Scorpio", "Ketu": "Taurus"}}, "D8": {"available": true, "lagna_sign": "Virgo", "planets": {"Sun": "Taurus", "Moon": "Capricorn", "Mars": "Leo", "Mercury": "Cancer", "Jupiter": "Libra", "Venus": "Leo", "Saturn": "Capricorn", "Rahu": "Taurus", "Ketu": "Scorpio"}}, "D9": {"available": true, "lagna_sign": "Capricorn", "planets": {"Sun": "Capricorn", "Moon": "Capricorn", "Mars": "Taurus", "Mercury": "Leo", "Jupiter": "Aquarius", "Venus": "Sagittarius", "Saturn": "Capricorn", "Rahu": "Gemini", "Ketu": "Sagittarius"}, "yogas": [{"name": "Raja Yoga", "components": ["Moon", "Saturn"]}]}, "D10": {"available": true, "lagna_sign": "Taurus", "planets": {"Sun": "Capricorn", "Moon": "Virgo", "Mars": "Libra", "Mercury": "Leo", "Jupiter": "Scorpio", "Venus": "Taurus", "Saturn": "Virgo", "Rahu": "Aquarius", "Ketu": "Leo"}, "yogas": []}, "D12": {"available": true, "lagna_sign": "Libra", "planets": {"Sun": "Taurus", "Moon": "Capricorn", "Mars": "Scorpio", "Mercury": "Virgo", "Jupiter": "Sagittarius", "Venus": "Libra", "Saturn": "Capricorn", "Rahu": "Leo", "Ketu": "Aquarius"}}, "D16": {"available": true, "lagna_sign": "Taurus", "planets": {"Sun": "Aries", "Moon": "Taurus", "Mars": "Taurus", "Mercury": "Scorpio", "Jupiter": "Sagittarius", "Venus": "Aquarius", "Saturn": "Aries", "Rahu": "Capricorn", "Ketu": "Capricorn"}}, "D20": {"available": true, "lagna_sign": "Taurus", "planets": {"Sun": "Aries", "Moon": "Taurus", "Mars": "Leo", "Mercury": "Capricorn", "Jupiter": "Aquarius", "Venus": "Aries", "Saturn": "Taurus", "Rahu": "Pisces", "Ketu": "Pisces"}}, "D24": {"available": true, "lagna_sign": "Virgo", "planets": {"Sun": "Cancer", "Moon": "Leo", "Mars": "Pisces", "Mercury": "Cancer", "Jupiter": "Leo", "Venus": "Libra", "Saturn": "Leo", "Rahu": "Virgo", "Ketu": "Virgo"}}, "D27": {"available": true, "lagna_sign": "Gemini", "planets": {"Sun": "Aries", "Moon": "Taurus", "Mars": "Aquarius", "Mercury": "Aries", "Jupiter": "Gemini", "Venus": "Virgo", "Saturn": "Taurus", "Rahu": "Cancer", "Ketu": "Cancer"}}, "D30": {"available": true, "lagna_sign": "Aries", "planets": {"Sun": "Aries", "Moon": "Aries", "Mars": "Gemini", "Mercury": "Sagittarius", "Jupiter": "Sagittarius", "Venus": "Gemini", "Saturn": "Aries", "Rahu": "Sagittarius", "Ketu": "Sagittarius"}}, "D40": {"available": true, "lagna_sign": "Cancer", "planets": {"Sun": "Aries", "Moon": "Gemini", "Mars": "Sagittarius", "Mercury": "Scorpio", "Jupiter": "Capricorn", "Venus": "Taurus", "Saturn": "Gemini", "Rahu": "Pisces", "Ketu": "Pisces"}}, "D45": {"available": true, "lagna_sign": "Leo", "planets": {"Sun": "Aries", "Moon": "Gemini", "Mars": "Aries", "Mercury": "Capricorn", "Jupiter": "Pisces", "Venus": "Leo", "Saturn": "Gemini", "Rahu": "Gemini", "Ketu": "Gemini"}}, "D60": {"available": true, "lagna_sign": "Aquarius", "planets": {"Sun": "Gemini", "Moon": "Aries", "Mars": "Pisces", "Mercury": "Leo", "Jupiter": "Capricorn", "Venus": "Aries", "Saturn": "Aries", "Rahu": "Sagittarius", "Ketu": "Gemini"}, "deities": {"Sun": "Bhramana", "Moon": "Amrita", "Mars": "Praveena", "Mercury": "Kamalakara", "Jupiter": "Kaala", "Venus": "Vishnu", "Saturn": "Amrita", "Rahu": "Deva", "Ketu": "Deva"}, "lagna_deity": "Krura"}}, "navamsha": {"ascendant": {"sign": "Capricorn"}, "Sun": {"sign": "Capricorn"}, "Moon": {"sign": "Capricorn"}, "Mars": {"sign": "Taurus"}, "Mercury": {"sign": "Leo"}, "Jupiter": {"sign": "Aquarius"}, "Venus": {"sign": "Sagittarius"}, "Saturn": {"sign": "Capricorn"}, "Rahu": {"sign": "Gemini"}, "Ketu": {"sign": "Sagittarius"}}, "graha_drishti": {"Sun": {"aspects_houses_from_self": [7], "aspected_signs": ["Scorpio"]}, "Moon": {"aspects_houses_from_self": [7], "aspected_signs": ["Cancer"]}, "Mars": {"aspects_houses_from_self": [4, 7, 8], "aspected_signs": ["Taurus", "Leo", "Virgo"]}, "Mercury": {"aspects_houses_from_self": [7], "aspected_signs": ["Libra"]}, "Jupiter": {"aspects_houses_from_self": [5, 7, 9], "aspected_signs": ["Libra", "Sagittarius", "Aquarius"]}, "Venus": {"aspects_houses_from_self": [7], "aspected_signs": ["Virgo"]}, "Saturn": {"aspects_houses_from_self": [3, 7, 10], "aspected_signs": ["Pisces", "Cancer", "Libra"]}, "Rahu": {"aspects_houses_from_self": [5, 7, 9], "aspected_signs": ["Taurus", "Cancer", "Virgo"]}, "Ketu": {"aspects_houses_from_self": [5, 7, 9], "aspected_signs": ["Scorpio", "Capricorn", "Pisces"]}}, "rasi_drishti": {"Aries": ["Leo", "Scorpio", "Aquarius"], "Taurus": ["Cancer", "Libra", "Capricorn"], "Gemini": ["Virgo", "Sagittarius", "Pisces"], "Cancer": ["Taurus", "Scorpio", "Aquarius"], "Leo": ["Aries", "Libra", "Capricorn"], "Virgo": ["Gemini", "Sagittarius", "Pisces"], "Libra": ["Taurus", "Leo", "Aquarius"], "Scorpio": ["Aries", "Cancer", "Capricorn"], "Sagittarius": ["Gemini", "Virgo", "Pisces"], "Capricorn": ["Taurus", "Leo", "Scorpio"], "Aquarius": ["Aries", "Cancer", "Libra"], "Pisces": ["Gemini", "Virgo", "Sagittarius"]}, "special_lagnas": {"available": true, "bhava_lagna": {"sign": "Virgo", "degrees_in_sign": 10.71}, "hora_lagna": {"sign": "Capricorn", "degrees_in_sign": 21.23}, "ghati_lagna": {"sign": "Aquarius", "degrees_in_sign": 22.77}, "sunrise_jd": 2448026.51246}, "shadbala": {"Sun": {"sthana_bala": 30, "dig_bala": 50.0, "kaala_bala": 30.0, "cheshta_bala": 0.0, "naisargika_bala": 60.0, "drig_bala": 15.0, "total_virupas": 185.0, "total_rupas": 3.08}, "Moon": {"sthana_bala": 30, "dig_bala": 50.0, "kaala_bala": 30.0, "cheshta_bala": 0.0, "naisargika_bala": 51.43, "drig_bala": 15.0, "total_virupas": 176.43, "total_rupas": 2.94}, "Mars": {"sthana_bala": 30, "dig_bala": 20.0, "kaala_bala": 30.0, "cheshta_bala": 20.0, "naisargika_bala": 17.14, "drig_bala": 15.0, "total_virupas": 132.14, "total_rupas": 2.2}, "Mercury": {"sthana_bala": 30, "dig_bala": 10.0, "kaala_bala": 30.0, "cheshta_bala": 45.0, "naisargika_bala": 25.7, "drig_bala": 15.0, "total_virupas": 155.7, "total_rupas": 2.59}, "Jupiter": {"sthana_bala": 30, "dig_bala": 30.0, "kaala_bala": 30.0, "cheshta_bala": 20.0, "naisargika_bala": 34.28, "drig_bala": 15.0, "total_virupas": 159.28, "total_rupas": 2.65}, "Venus": {"sthana_bala": 60, "dig_bala": 30.0, "kaala_bala": 30.0, "cheshta_bala": 20.0, "naisargika_bala": 42.85, "drig_bala": 15.0, "total_virupas": 197.85, "total_rupas": 3.3}, "Saturn": {"sthana_bala": 45, "dig_bala": 40.0, "kaala_bala": 30.0, "cheshta_bala": 45.0, "naisargika_bala": 8.57, "drig_bala": 15.0, "total_virupas": 183.57, "total_rupas": 3.06}}, "arudha_padas": {"AL": "Scorpio", "A2": "Leo", "A3": "Taurus", "A4": "Pisces", "A5": "Libra", "A6": "Sagittarius", "A7": "Virgo", "A8": "Sagittarius", "A9": "Capricorn", "A10": "Aquarius", "A11": "Libra", "A12": "Aquarius", "UL": "Aquarius"}, "chara_karakas": {"AK": {"planet": "Mars", "sort_value": 24.5152, "karakamsha_sign": "Taurus"}, "AmK": {"planet": "Venus", "sort_value": 18.9499}, "BK": {"planet": "Jupiter", "sort_value": 15.7923}, "MK": {"planet": "Mercury", "sort_value": 14.3023}, "PiK": {"planet": "Rahu", "sort_value": 13.47}, "PK": {"planet": "Moon", "sort_value": 1.8935}, "GK": {"planet": "Saturn", "sort_value": 1.5257}, "DK": {"planet": "Sun", "sort_value": 0.5498}, "_meta": {"system": "Parashari 8-planet", "ketu_excluded": true, "rahu_uses_true_node": true, "tie_skipped_degrees": null}, "karakamsha_sign": "Taurus"}, "ashtakavarga": {"individual": {"Sun": {"Aries": 2, "Taurus": 2, "Gemini": 4, "Cancer": 2, "Leo": 6, "Virgo": 4, "Libra": 4, "Scorpio": 6, "Sagittarius": 4, "Capricorn": 3, "Aquarius": 7, "Pisces": 4}, "Moon": {"Aries": 3, "Taurus": 3, "Gemini": 7, "Cancer": 6, "Leo": 1, "Virgo": 2, "Libra": 4, "Scorpio": 7, "Sagittarius": 4, "Capricorn": 4, "Aquarius": 3, "Pisces": 5}, "Mars": {"Aries": 2, "Taurus": 2, "Gemini": 3, "Cancer": 3, "Leo": 4, "Virgo": 5, "Libra": 3, "Scorpio": 5, "Sagittarius": 1, "Capricorn": 2, "Aquarius": 5, "Pisces": 4}, "Mercury": {"Aries": 7, "Taurus": 3, "Gemini": 4, "Cancer": 3, "Leo": 4, "Virgo": 5, "Libra": 6, "Scorpio": 5, "Sagittarius": 3, "Capricorn": 5, "Aquarius": 5, "Pisces": 4}, "Jupiter": {"Aries": 3, "Taurus": 6, "Gemini": 4, "Cancer": 6, "Leo": 5, "Virgo": 5, "Libra": 1, "Scorpio": 4, "Sagittarius": 7, "Capricorn": 5, "Aquarius": 5, "Pisces": 5}, "Venus": {"Aries": 7, "Taurus": 4, "Gemini": 3, "Cancer": 3, "Leo": 3, "Virgo": 4, "Libra": 5, "Scorpio": 4, "Sagittarius": 6, "Capricorn": 5, "Aquarius": 3, "Pisces": 5}, "Saturn": {"Aries": 2, "Taurus": 3, "Gemini": 5, "Cancer": 2, "Leo": 2, "Virgo": 2, "Libra": 1, "Scorpio": 7, "Sagittarius": 4, "Capricorn": 3, "Aquarius": 4, "Pisces": 4}}, "samudaya": {"Aries": 26, "Taurus": 23, "Gemini": 30, "Cancer": 25, "Leo": 25, "Virgo": 27, "Libra": 24, "Scorpio": 38, "Sagittarius": 29, "Capricorn": 27, "Aquarius": 32, "Pisces": 31}, "samudaya_array": [26, 23, 30, 25, 25, 27, 24, 38, 29, 27, 32, 31], "samudaya_total": 337, "reduced_individual": {"Sun": {"Aries": 0, "Taurus": 0, "Gemini": 0, "Cancer": 0, "Leo": 4, "Virgo": 0, "Libra": 0, "Scorpio": 0, "Sagittarius": 0, "Capricorn": 0, "Aquarius": 2, "Pisces": 0}, "Moon": {"Aries": 0, "Taurus": 0, "Gemini": 0, "Cancer": 1, "Leo": 0, "Virgo": 0, "Libra": 0, "Scorpio": 0, "Sagittarius": 0, "Capricorn": 0, "Aquarius": 0, "Pisces": 0}, "Mars": {"Aries": 0, "Taurus": 0, "Gemini": 0, "Cancer": 0, "Leo": 3, "Virgo": 0, "Libra": 0, "Scorpio": 1, "Sagittarius": 0, "Capricorn": 0, "Aquarius": 0, "Pisces": 0}, "Mercury": {"Aries": 2, "Taurus": 0, "Gemini": 0, "Cancer": 0, "Leo": 1, "Virgo": 0, "Libra": 0, "Scorpio": 0, "Sagittarius": 0, "Capricorn": 1, "Aquarius": 0, "Pisces": 0}, "Jupiter": {"Aries": 0, "Taurus": 0, "Gemini": 0, "Cancer": 2, "Leo": 2, "Virgo": 0, "Libra": 0, "Scorpio": 0, "Sagittarius": 3, "Capricorn": 0, "Aquarius": 0, "Pisces": 0}, "Venus": {"Aries": 3, "Taurus": 0, "Gemini": 0, "Cancer": 0, "Leo": 0, "Virgo": 0, "Libra": 0, "Scorpio": 0, "Sagittarius": 1, "Capricorn": 0, "Aquarius": 0, "Pisces": 0}, "Saturn": {"Aries": 0, "Taurus": 0, "Gemini": 0, "Cancer": 0, "Leo": 0, "Virgo": 0, "Libra": 0, "Scorpio": 0, "Sagittarius": 0, "Capricorn": 0, "Aquarius": 2, "Pisces": 0}}, "shodhya_pinda": {"Sun": 0, "Moon": 0, "Mars": 0, "Mercury": 24, "Jupiter": 0, "Venus": 0, "Saturn": 0}, "strongest_periods": ["Mercury", "Sun", "Moon"], "weakest_periods": ["Venus", "Saturn"], "note": "SAV always sums to 337; a sign with >=28 bindus is strong. Shodhya Pinda computed after Trikona + Ekadhipatya reductions."}, "yogas": [{"name": "Malavya Yoga (Mahapurusha)", "components": ["Venus"], "strength": "strong", "life_area": "character", "mitigated": false}, {"name": "Amala Yoga", "components": ["Jupiter"], "strength": "medium", "life_area": "reputation", "mitigated": false}, {"name": "Vipreet Raja Yoga (Sarala)", "components": ["Mars"], "strength": "medium", "life_area": "rise through adversity", "mitigated": false}, {"name": "Dhana Yoga", "components": ["Moon", "Saturn"], "strength": "medium", "life_area": "wealth", "mitigated": false}], "conditional_dashas": {"dwi_saptati_sama": {"applies": false, "cycle_years": 72, "trigger": "Lagna lord in 7th, or 7th lord in Lagna", "governor": "Moon"}, "shat_trimsa_sama": {"applies": true, "cycle_years": 36, "trigger": "hora-birth (daytime \u2192 Sun's hora / nighttime \u2192 Moon's hora)", "source_note": "conditionally interpreted; BPHS translators differ"}, "applicable": true, "note": "Vimshottari remains primary; conditional dashas are secondary indicators."}, "narayana_dasha": {"dasha_lagna_d1": "Pisces", "d1": [{"sign": "Pisces", "sign_lord": "Jupiter", "direction": "forward", "sub_period_rule": "aspecting/occupying (Rasi Drishti) \u2192 sign \u2192 sign-lord", "three_parts": [{"part": 1, "driver": "aspecting_or_occupying", "of": ["Jupiter", "Venus"]}, {"part": 2, "driver": "sign", "of": "Pisces"}, {"part": 3, "driver": "sign_lord", "of": "Jupiter"}], "antardasha_sequence": ["Gemini", "Cancer", "Leo", "Virgo", "Libra", "Scorpio", "Sagittarius", "Capricorn", "Aquarius", "Pisces", "Aries", "Taurus"], "start": "1990-05-15", "end": "1994-05-15"}, {"sign": "Aries", "sign_lord": "Mars", "direction": "forward", "sub_period_rule": "sign \u2192 sign-lord \u2192 aspecting/occupying (Rasi Drishti)", "three_parts": [{"part": 1, "driver": "sign", "of": "Aries"}, {"part": 2, "driver": "sign_lord", "of": "Mars"}, {"part": 3, "driver": "aspecting_or_occupying", "of": ["Mars", "Mercury"]}], "antardasha_sequence": ["Aquarius", "Pisces", "Aries", "Taurus", "Gemini", "Cancer", "Leo", "Virgo", "Libra", "Scorpio", "Sagittarius", "Capricorn"], "start": "1994-05-15", "end": "2005-05-15"}, {"sign": "Taurus", "sign_lord": "Venus", "direction": "forward", "sub_period_rule": "sign-lord \u2192 sign \u2192 aspecting/occupying (Rasi Drishti)", "three_parts": [{"part": 1, "driver": "sign_lord", "of": "Venus"}, {"part": 2, "driver": "sign", "of": "Taurus"}, {"part": 3, "driver": "aspecting_or_occupying", "of": ["Ketu", "Moon", "Rahu", "Saturn", "Sun"]}], "antardasha_sequence": ["Pisces", "Aquarius", "Capricorn", "Sagittarius", "Scorpio", "Libra", "Virgo", "Leo", "Cancer", "Gemini", "Taurus", "Aries"], "start": "2005-05-15", "end": "2008-05-15"}, {"sign": "Gemini", "sign_lord": "Mercury", "direction": "forward", "sub_period_rule": "aspecting/occupying (Rasi Drishti) \u2192 sign \u2192 sign-lord", "three_parts": [{"part": 1, "driver": "aspecting_or_occupying", "of": ["Jupiter", "Venus"]}, {"part": 2, "driver": "sign", "of": "Gemini"}, {"part": 3, "driver": "sign_lord", "of": "Mercury"}], "antardasha_sequence": ["Aries", "Taurus", "Gemini", "Cancer", "Leo", "Virgo", "Libra", "Scorpio", "Sagittarius", "Capricorn", "Aquarius", "Pisces"], "start": "2008-05-15", "end": "2019-05-15"}, {"sign": "Cancer", "sign_lord": "Moon", "direction": "forward", "sub_period_rule": "sign \u2192 sign-lord \u2192 aspecting/occupying (Rasi Drishti)", "three_parts": [{"part": 1, "driver": "sign", "of": "Cancer"}, {"part": 2, "driver": "sign_lord", "of": "Moon"}, {"part": 3, "driver": "aspecting_or_occupying", "of": ["Ketu", "Mars", "Sun"]}], "antardasha_sequence": ["Capricorn", "Sagittarius", "Scorpio", "Libra", "Virgo", "Leo", "Cancer", "Gemini", "Taurus", "Aries", "Pisces", "Aquarius"], "start": "2019-05-15", "end": "2026-05-15"}, {"sign": "Leo", "sign_lord": "Sun", "direction": "forward", "sub_period_rule": "sign-lord \u2192 sign \u2192 aspecting/occupying (Rasi Drishti)", "three_parts": [{"part": 1, "driver": "sign_lord", "of": "Sun"}, {"part": 2, "driver": "sign", "of": "Leo"}, {"part": 3, "driver": "aspecting_or_occupying", "of": ["Mercury", "Moon", "Rahu", "Saturn"]}], "antardasha_sequence": ["Capricorn", "Sagittarius", "Scorpio", "Libra", "Virgo", "Leo", "Cancer", "Gemini", "Taurus", "Aries", "Pisces", "Aquarius"], "start": "2026-05-15", "end": "2030-05-15"}, {"sign": "Virgo", "sign_lord": "Mercury", "direction": "forward", "sub_period_rule": "aspecting/occupying (Rasi Drishti) \u2192 sign \u2192 sign-lord", "three_parts": [{"part": 1, "driver": "aspecting_or_occupying", "of": ["Jupiter", "Venus"]}, {"part": 2, "driver": "sign", "of": "Virgo"}, {"part": 3, "driver": "sign_lord", "of": "Mercury"}], "antardasha_sequence": ["Gemini", "Cancer", "Leo", "Virgo", "Libra", "Scorpio", "Sagittarius", "Capricorn", "Aquarius", "Pisces", "Aries", "Taurus"], "start": "2030-05-15", "end": "2038-05-15"}, {"sign": "Libra", "sign_lord": "Venus", "direction": "forward", "sub_period_rule": "sign \u2192 sign-lord \u2192 aspecting/occupying (Rasi Drishti)", "three_parts": [{"part": 1, "driver": "sign", "of": "Libra"}, {"part": 2, "driver": "sign_lord", "of": "Venus"}, {"part": 3, "driver": "aspecting_or_occupying", "of": ["Mars", "Sun"]}], "antardasha_sequence": ["Aquarius", "Pisces", "Aries", "Taurus", "Gemini", "Cancer", "Leo", "Virgo", "Libra", "Scorpio", "Sagittarius", "Capricorn"], "start": "2038-05-15", "end": "2044-05-15"}, {"sign": "Scorpio", "sign_lord": "Mars", "direction": "forward", "sub_period_rule": "sign-lord \u2192 sign \u2192 aspecting/occupying (Rasi Drishti)", "three_parts": [{"part": 1, "driver": "sign_lord", "of": "Mars"}, {"part": 2, "driver": "sign", "of": "Scorpio"}, {"part": 3, "driver": "aspecting_or_occupying", "of": ["Ketu", "Mercury", "Moon", "Rahu", "Saturn"]}], "antardasha_sequence": ["Pisces", "Aquarius", "Capricorn", "Sagittarius", "Scorpio", "Libra", "Virgo", "Leo", "Cancer", "Gemini", "Taurus", "Aries"], "start": "2044-05-15", "end": "2054-05-15"}, {"sign": "Sagittarius", "sign_lord": "Jupiter", "direction": "forward", "sub_period_rule": "aspecting/occupying (Rasi Drishti) \u2192 sign \u2192 sign-lord", "three_parts": [{"part": 1, "driver": "aspecting_or_occupying", "of": ["Jupiter", "Venus"]}, {"part": 2, "driver": "sign", "of": "Sagittarius"}, {"part": 3, "driver": "sign_lord", "of": "Jupiter"}], "antardasha_sequence": ["Aries", "Taurus", "Gemini", "Cancer", "Leo", "Virgo", "Libra", "Scorpio", "Sagittarius", "Capricorn", "Aquarius", "Pisces"], "start": "2054-05-15", "end": "2061-05-15"}, {"sign": "Capricorn", "sign_lord": "Saturn", "direction": "forward", "sub_period_rule": "sign \u2192 sign-lord \u2192 aspecting/occupying (Rasi Drishti)", "three_parts": [{"part": 1, "driver": "sign", "of": "Capricorn"}, {"part": 2, "driver": "sign_lord", "of": "Saturn"}, {"part": 3, "driver": "aspecting_or_occupying", "of": ["Moon", "Rahu", "Saturn", "Sun"]}], "antardasha_sequence": ["Capricorn", "Sagittarius", "Scorpio", "Libra", "Virgo", "Leo", "Cancer", "Gemini", "Taurus", "Aries", "Pisces", "Aquarius"], "start": "2061-05-15", "end": "2073-05-15"}, {"sign": "Aquarius", "sign_lord": "Saturn", "direction": "forward", "sub_period_rule": "sign-lord \u2192 sign \u2192 aspecting/occupying (Rasi Drishti)", "three_parts": [{"part": 1, "driver": "sign_lord", "of": "Saturn"}, {"part": 2, "driver": "sign", "of": "Aquarius"}, {"part": 3, "driver": "aspecting_or_occupying", "of": ["Ketu", "Mars", "Mercury"]}], "antardasha_sequence": ["Capricorn", "Sagittarius", "Scorpio", "Libra", "Virgo", "Leo", "Cancer", "Gemini", "Taurus", "Aries", "Pisces", "Aquarius"], "start": "2073-05-15", "end": "2075-05-15"}], "dasha_lagna_d9": "Capricorn", "d9": [{"sign": "Capricorn", "sign_lord": "Saturn", "direction": "forward", "sub_period_rule": "sign \u2192 sign-lord \u2192 aspecting/occupying (Rasi Drishti)", "three_parts": [{"part": 1, "driver": "sign", "of": "Capricorn"}, {"part": 2, "driver": "sign_lord", "of": "Saturn"}, {"part": 3, "driver": "aspecting_or_occupying", "of": ["Mars", "Mercury", "Moon", "Saturn", "Sun"]}], "antardasha_sequence": ["Capricorn", "Sagittarius", "Scorpio", "Libra", "Virgo", "Leo", "Cancer", "Gemini", "Taurus", "Aries", "Pisces", "Aquarius"], "start": "1990-05-15", "end": "2002-05-15"}, {"sign": "Aquarius", "sign_lord": "Saturn", "direction": "forward", "sub_period_rule": "sign-lord \u2192 sign \u2192 aspecting/occupying (Rasi Drishti)", "three_parts": [{"part": 1, "driver": "sign_lord", "of": "Saturn"}, {"part": 2, "driver": "sign", "of": "Aquarius"}, {"part": 3, "driver": "aspecting_or_occupying", "of": ["Jupiter"]}], "antardasha_sequence": ["Capricorn", "Sagittarius", "Scorpio", "Libra", "Virgo", "Leo", "Cancer", "Gemini", "Taurus", "Aries", "Pisces", "Aquarius"], "start": "2002-05-15", "end": "2004-05-15"}, {"sign": "Pisces", "sign_lord": "Jupiter", "direction": "forward", "sub_period_rule": "aspecting/occupying (Rasi Drishti) \u2192 sign \u2192 sign-lord", "three_parts": [{"part": 1, "driver": "aspecting_or_occupying", "of": ["Ketu", "Rahu", "Venus"]}, {"part": 2, "driver": "sign", "of": "Pisces"}, {"part": 3, "driver": "sign_lord", "of": "Jupiter"}], "antardasha_sequence": ["Aquarius", "Pisces", "Aries", "Taurus", "Gemini", "Cancer", "Leo", "Virgo", "Libra", "Scorpio", "Sagittarius", "Capricorn"], "start": "2004-05-15", "end": "2016-05-15"}, {"sign": "Aries", "sign_lord": "Mars", "direction": "forward", "sub_period_rule": "sign \u2192 sign-lord \u2192 aspecting/occupying (Rasi Drishti)", "three_parts": [{"part": 1, "driver": "sign", "of": "Aries"}, {"part": 2, "driver": "sign_lord", "of": "Mars"}, {"part": 3, "driver": "aspecting_or_occupying", "of": ["Jupiter", "Mercury"]}], "antardasha_sequence": ["Taurus", "Aries", "Pisces", "Aquarius", "Capricorn", "Sagittarius", "Scorpio", "Libra", "Virgo", "Leo", "Cancer", "Gemini"], "start": "2016-05-15", "end": "2018-05-15"}, {"sign": "Taurus", "sign_lord": "Venus", "direction": "forward", "sub_period_rule": "sign-lord \u2192 sign \u2192 aspecting/occupying (Rasi Drishti)", "three_parts": [{"part": 1, "driver": "sign_lord", "of": "Venus"}, {"part": 2, "driver": "sign", "of": "Taurus"}, {"part": 3, "driver": "aspecting_or_occupying", "of": ["Mars", "Moon", "Saturn", "Sun"]}], "antardasha_sequence": ["Sagittarius", "Capricorn", "Aquarius", "Pisces", "Aries", "Taurus", "Gemini", "Cancer", "Leo", "Virgo", "Libra", "Scorpio"], "start": "2018-05-15", "end": "2024-05-15"}, {"sign": "Gemini", "sign_lord": "Mercury", "direction": "forward", "sub_period_rule": "aspecting/occupying (Rasi Drishti) \u2192 sign \u2192 sign-lord", "three_parts": [{"part": 1, "driver": "aspecting_or_occupying", "of": ["Ketu", "Rahu", "Venus"]}, {"part": 2, "driver": "sign", "of": "Gemini"}, {"part": 3, "driver": "sign_lord", "of": "Mercury"}], "antardasha_sequence": ["Aquarius", "Pisces", "Aries", "Taurus", "Gemini", "Cancer", "Leo", "Virgo", "Libra", "Scorpio", "Sagittarius", "Capricorn"], "start": "2024-05-15", "end": "2027-05-15"}, {"sign": "Cancer", "sign_lord": "Moon", "direction": "forward", "sub_period_rule": "sign \u2192 sign-lord \u2192 aspecting/occupying (Rasi Drishti)", "three_parts": [{"part": 1, "driver": "sign", "of": "Cancer"}, {"part": 2, "driver": "sign_lord", "of": "Moon"}, {"part": 3, "driver": "aspecting_or_occupying", "of": ["Jupiter", "Mars"]}], "antardasha_sequence": ["Capricorn", "Sagittarius", "Scorpio", "Libra", "Virgo", "Leo", "Cancer", "Gemini", "Taurus", "Aries", "Pisces", "Aquarius"], "start": "2027-05-15", "end": "2034-05-15"}, {"sign": "Leo", "sign_lord": "Sun", "direction": "forward", "sub_period_rule": "sign-lord \u2192 sign \u2192 aspecting/occupying (Rasi Drishti)", "three_parts": [{"part": 1, "driver": "sign_lord", "of": "Sun"}, {"part": 2, "driver": "sign", "of": "Leo"}, {"part": 3, "driver": "aspecting_or_occupying", "of": ["Mercury", "Moon", "Saturn", "Sun"]}], "antardasha_sequence": ["Capricorn", "Sagittarius", "Scorpio", "Libra", "Virgo", "Leo", "Cancer", "Gemini", "Taurus", "Aries", "Pisces", "Aquarius"], "start": "2034-05-15", "end": "2042-05-15"}, {"sign": "Virgo", "sign_lord": "Mercury", "direction": "forward", "sub_period_rule": "aspecting/occupying (Rasi Drishti) \u2192 sign \u2192 sign-lord", "three_parts": [{"part": 1, "driver": "aspecting_or_occupying", "of": ["Ketu", "Rahu", "Venus"]}, {"part": 2, "driver": "sign", "of": "Virgo"}, {"part": 3, "driver": "sign_lord", "of": "Mercury"}], "antardasha_sequence": ["Leo", "Virgo", "Libra", "Scorpio", "Sagittarius", "Capricorn", "Aquarius", "Pisces", "Aries", "Taurus", "Gemini", "Cancer"], "start": "2042-05-15", "end": "2054-05-15"}, {"sign": "Libra", "sign_lord": "Venus", "direction": "forward", "sub_period_rule": "sign \u2192 sign-lord \u2192 aspecting/occupying (Rasi Drishti)", "three_parts": [{"part": 1, "driver": "sign", "of": "Libra"}, {"part": 2, "driver": "sign_lord", "of": "Venus"}, {"part": 3, "driver": "aspecting_or_occupying", "of": ["Jupiter", "Mars", "Mercury"]}], "antardasha_sequence": ["Sagittarius", "Capricorn", "Aquarius", "Pisces", "Aries", "Taurus", "Gemini", "Cancer", "Leo", "Virgo", "Libra", "Scorpio"], "start": "2054-05-15", "end": "2057-05-15"}, {"sign": "Scorpio", "sign_lord": "Mars", "direction": "forward", "sub_period_rule": "sign-lord \u2192 sign \u2192 aspecting/occupying (Rasi Drishti)", "three_parts": [{"part": 1, "driver": "sign_lord", "of": "Mars"}, {"part": 2, "driver": "sign", "of": "Scorpio"}, {"part": 3, "driver": "aspecting_or_occupying", "of": ["Moon", "Saturn", "Sun"]}], "antardasha_sequence": ["Sagittarius", "Capricorn", "Aquarius", "Pisces", "Aries", "Taurus", "Gemini", "Cancer", "Leo", "Virgo", "Libra", "Scorpio"], "start": "2057-05-15", "end": "2064-05-15"}, {"sign": "Sagittarius", "sign_lord": "Jupiter", "direction": "forward", "sub_period_rule": "aspecting/occupying (Rasi Drishti) \u2192 sign \u2192 sign-lord", "three_parts": [{"part": 1, "driver": "aspecting_or_occupying", "of": ["Ketu", "Rahu", "Venus"]}, {"part": 2, "driver": "sign", "of": "Sagittarius"}, {"part": 3, "driver": "sign_lord", "of": "Jupiter"}], "antardasha_sequence": ["Aquarius", "Pisces", "Aries", "Taurus", "Gemini", "Cancer", "Leo", "Virgo", "Libra", "Scorpio", "Sagittarius", "Capricorn"], "start": "2064-05-15", "end": "2067-05-15"}]}, "varshaphala": {"2026": {"year": 2026, "varsha_lagna": {"sign": "Scorpio", "degrees_in_sign": 19.64}, "muntha": {"sign": "Virgo", "house": 1}, "varsheshwara": "Mars", "mudda_dasha": [{"lord": "Sun", "start": "2026-05-15", "end": "2026-06-02"}, {"lord": "Moon", "start": "2026-06-02", "end": "2026-07-03"}, {"lord": "Mars", "start": "2026-07-03", "end": "2026-07-24"}, {"lord": "Rahu", "start": "2026-07-24", "end": "2026-09-17"}, {"lord": "Jupiter", "start": "2026-09-17", "end": "2026-11-05"}, {"lord": "Saturn", "start": "2026-11-05", "end": "2027-01-01"}, {"lord": "Mercury", "start": "2027-01-01", "end": "2027-02-22"}, {"lord": "Ketu", "start": "2027-02-22", "end": "2027-03-15"}, {"lord": "Venus", "start": "2027-03-15", "end": "2027-05-15"}], "note": "Varsheshwara via Varsha-Lagna lord; full Panchavargiya Bala scoring flagged for QA."}, "2027": {"year": 2027, "varsha_lagna": {"sign": "Aquarius", "degrees_in_sign": 22.52}, "muntha": {"sign": "Libra", "house": 2}, "varsheshwara": "Saturn", "mudda_dasha": [{"lord": "Sun", "start": "2027-05-15", "end": "2027-06-03"}, {"lord": "Moon", "start": "2027-06-03", "end": "2027-07-03"}, {"lord": "Mars", "start": "2027-07-03", "end": "2027-07-24"}, {"lord": "Rahu", "start": "2027-07-24", "end": "2027-09-17"}, {"lord": "Jupiter", "start": "2027-09-17", "end": "2027-11-05"}, {"lord": "Saturn", "start": "2027-11-05", "end": "2028-01-02"}, {"lord": "Mercury", "start": "2028-01-02", "end": "2028-02-22"}, {"lord": "Ketu", "start": "2028-02-22", "end": "2028-03-15"}, {"lord": "Venus", "start": "2028-03-15", "end": "2028-05-15"}], "note": "Varsheshwara via Varsha-Lagna lord; full Panchavargiya Bala scoring flagged for QA."}}, "vimshottari": {"balance_at_birth": {"lord": "Sun", "years_remaining": 3.648}, "timeline": [{"maha_lord": "Sun", "start": "1990-05-15", "end": "1994-01-07", "antardashas": [{"lord": "Jupiter", "start": "1990-05-15", "end": "1990-11-13"}, {"lord": "Saturn", "start": "1990-11-13", "end": "1991-10-26"}, {"lord": "Mercury", "start": "1991-10-26", "end": "1992-08-31"}, {"lord": "Ketu", "start": "1992-08-31", "end": "1993-01-06"}, {"lord": "Venus", "start": "1993-01-06", "end": "1994-01-07"}]}, {"maha_lord": "Moon", "start": "1994-01-07", "end": "2004-01-07", "antardashas": [{"lord": "Moon", "start": "1994-01-07", "end": "1994-11-07"}, {"lord": "Mars", "start": "1994-11-07", "end": "1995-06-08"}, {"lord": "Rahu", "start": "1995-06-08", "end": "1996-12-07"}, {"lord": "Jupiter", "start": "1996-12-07", "end": "1998-04-08"}, {"lord": "Saturn", "start": "1998-04-08", "end": "1999-11-07"}, {"lord": "Mercury", "start": "1999-11-07", "end": "2001-04-08"}, {"lord": "Ketu", "start": "2001-04-08", "end": "2001-11-07"}, {"lord": "Venus", "start": "2001-11-07", "end": "2003-07-08"}, {"lord": "Sun", "start": "2003-07-08", "end": "2004-01-07"}]}, {"maha_lord": "Mars", "start": "2004-01-07", "end": "2011-01-07", "antardashas": [{"lord": "Mars", "start": "2004-01-07", "end": "2004-06-04"}, {"lord": "Rahu", "start": "2004-06-04", "end": "2005-06-23"}, {"lord": "Jupiter", "start": "2005-06-23", "end": "2006-05-30"}, {"lord": "Saturn", "start": "2006-05-30", "end": "2007-07-08"}, {"lord": "Mercury", "start": "2007-07-08", "end": "2008-07-05"}, {"lord": "Ketu", "start": "2008-07-05", "end": "2008-12-01"}, {"lord": "Venus", "start": "2008-12-01", "end": "2010-01-31"}, {"lord": "Sun", "start": "2010-01-31", "end": "2010-06-08"}, {"lord": "Moon", "start": "2010-06-08", "end": "2011-01-07"}]}, {"maha_lord": "Rahu", "start": "2011-01-07", "end": "2029-01-06", "antardashas": [{"lord": "Rahu", "start": "2011-01-07", "end": "2013-09-19"}, {"lord": "Jupiter", "start": "2013-09-19", "end": "2016-02-13"}, {"lord": "Saturn", "start": "2016-02-13", "end": "2018-12-19"}, {"lord": "Mercury", "start": "2018-12-19", "end": "2021-07-08"}, {"lord": "Ketu", "start": "2021-07-08", "end": "2022-07-26"}, {"lord": "Venus", "start": "2022-07-26", "end": "2025-07-26"}, {"lord": "Sun", "start": "2025-07-26", "end": "2026-06-20"}, {"lord": "Moon", "start": "2026-06-20", "end": "2027-12-20"}, {"lord": "Mars", "start": "2027-12-20", "end": "2029-01-06"}]}, {"maha_lord": "Jupiter", "start": "2029-01-06", "end": "2045-01-06", "antardashas": [{"lord": "Jupiter", "start": "2029-01-06", "end": "2031-02-24"}, {"lord": "Saturn", "start": "2031-02-24", "end": "2033-09-07"}, {"lord": "Mercury", "start": "2033-09-07", "end": "2035-12-14"}, {"lord": "Ketu", "start": "2035-12-14", "end": "2036-11-19"}, {"lord": "Venus", "start": "2036-11-19", "end": "2039-07-21"}, {"lord": "Sun", "start": "2039-07-21", "end": "2040-05-08"}, {"lord": "Moon", "start": "2040-05-08", "end": "2041-09-07"}, {"lord": "Mars", "start": "2041-09-07", "end": "2042-08-14"}, {"lord": "Rahu", "start": "2042-08-14", "end": "2045-01-06"}]}, {"maha_lord": "Saturn", "start": "2045-01-06", "end": "2064-01-07", "antardashas": [{"lord": "Saturn", "start": "2045-01-06", "end": "2048-01-10"}, {"lord": "Mercury", "start": "2048-01-10", "end": "2050-09-19"}, {"lord": "Ketu", "start": "2050-09-19", "end": "2051-10-29"}, {"lord": "Venus", "start": "2051-10-29", "end": "2054-12-29"}, {"lord": "Sun", "start": "2054-12-29", "end": "2055-12-11"}, {"lord": "Moon", "start": "2055-12-11", "end": "2057-07-11"}, {"lord": "Mars", "start": "2057-07-11", "end": "2058-08-20"}, {"lord": "Rahu", "start": "2058-08-20", "end": "2061-06-26"}, {"lord": "Jupiter", "start": "2061-06-26", "end": "2064-01-07"}]}, {"maha_lord": "Mercury", "start": "2064-01-07", "end": "2081-01-06", "antardashas": [{"lord": "Mercury", "start": "2064-01-07", "end": "2066-06-05"}, {"lord": "Ketu", "start": "2066-06-05", "end": "2067-06-02"}, {"lord": "Venus", "start": "2067-06-02", "end": "2070-04-02"}, {"lord": "Sun", "start": "2070-04-02", "end": "2071-02-06"}, {"lord": "Moon", "start": "2071-02-06", "end": "2072-07-08"}, {"lord": "Mars", "start": "2072-07-08", "end": "2073-07-05"}, {"lord": "Rahu", "start": "2073-07-05", "end": "2076-01-22"}, {"lord": "Jupiter", "start": "2076-01-22", "end": "2078-04-29"}, {"lord": "Saturn", "start": "2078-04-29", "end": "2081-01-06"}]}]}, "current_periods": {"current_maha": "Rahu", "current_maha_end": "2029-01-06", "current_antar": "Sun", "current_antar_end": "2026-06-20", "next_antar": "Moon", "next_antar_start": "2026-06-20"}}, "kp": {"ayanamsha": "Krishnamurti (KP)", "house_system": "Placidus", "planets": {"Sun": {"longitude": 30.6466, "sign": "Taurus", "sign_lord": "Venus", "star_lord": "Sun", "sub_lord": "Rahu", "sub_sub_lord": "Venus"}, "Moon": {"longitude": 271.9904, "sign": "Capricorn", "sign_lord": "Saturn", "star_lord": "Sun", "sub_lord": "Jupiter", "sub_sub_lord": "Mercury"}, "Mars": {"longitude": 324.6121, "sign": "Aquarius", "sign_lord": "Saturn", "star_lord": "Jupiter", "sub_lord": "Mercury", "sub_sub_lord": "Sun"}, "Mercury": {"longitude": 14.3991, "sign": "Aries", "sign_lord": "Mars", "star_lord": "Venus", "sub_lord": "Venus", "sub_sub_lord": "Rahu"}, "Jupiter": {"longitude": 75.8891, "sign": "Gemini", "sign_lord": "Mercury", "star_lord": "Rahu", "sub_lord": "Venus", "sub_sub_lord": "Mars"}, "Venus": {"longitude": 349.0468, "sign": "Pisces", "sign_lord": "Jupiter", "star_lord": "Mercury", "sub_lord": "Ketu", "sub_sub_lord": "Jupiter"}, "Saturn": {"longitude": 271.6226, "sign": "Capricorn", "sign_lord": "Saturn", "star_lord": "Sun", "sub_lord": "Jupiter", "sub_sub_lord": "Saturn"}, "Rahu": {"longitude": 287.7168, "sign": "Capricorn", "sign_lord": "Saturn", "star_lord": "Moon", "sub_lord": "Saturn", "sub_sub_lord": "Jupiter"}, "Ketu": {"longitude": 107.7168, "sign": "Cancer", "sign_lord": "Moon", "star_lord": "Mercury", "sub_lord": "Mercury", "sub_sub_lord": "Mars"}}, "cusps": [{"house": 1, "longitude": 152.8396, "sign": "Virgo", "sign_lord": "Mercury", "star_lord": "Sun", "sub_lord": "Jupiter", "sub_sub_lord": "Rahu"}, {"house": 2, "longitude": 182.4619, "sign": "Libra", "sign_lord": "Venus", "star_lord": "Mars", "sub_lord": "Ketu", "sub_sub_lord": "Saturn"}, {"house": 3, "longitude": 212.8904, "sign": "Scorpio", "sign_lord": "Mars", "star_lord": "Jupiter", "sub_lord": "Rahu", "sub_sub_lord": "Venus"}, {"house": 4, "longitude": 242.9938, "sign": "Sagittarius", "sign_lord": "Jupiter", "star_lord": "Ketu", "sub_lord": "Venus", "sub_sub_lord": "Ketu"}, {"house": 5, "longitude": 272.9475, "sign": "Capricorn", "sign_lord": "Saturn", "star_lord": "Sun", "sub_lord": "Jupiter", "sub_sub_lord": "Rahu"}, {"house": 6, "longitude": 303.1426, "sign": "Aquarius", "sign_lord": "Saturn", "star_lord": "Mars", "sub_lord": "Venus", "sub_sub_lord": "Sun"}, {"house": 7, "longitude": 332.8396, "sign": "Pisces", "sign_lord": "Jupiter", "star_lord": "Jupiter", "sub_lord": "Rahu", "sub_sub_lord": "Venus"}, {"house": 8, "longitude": 2.4619, "sign": "Aries", "sign_lord": "Mars", "star_lord": "Ketu", "sub_lord": "Venus", "sub_sub_lord": "Saturn"}, {"house": 9, "longitude": 32.8904, "sign": "Taurus", "sign_lord": "Venus", "star_lord": "Sun", "sub_lord": "Jupiter", "sub_sub_lord": "Rahu"}, {"house": 10, "longitude": 62.9938, "sign": "Gemini", "sign_lord": "Mercury", "star_lord": "Mars", "sub_lord": "Venus", "sub_sub_lord": "Venus"}, {"house": 11, "longitude": 92.9475, "sign": "Cancer", "sign_lord": "Moon", "star_lord": "Jupiter", "sub_lord": "Rahu", "sub_sub_lord": "Venus"}, {"house": 12, "longitude": 123.1426, "sign": "Leo", "sign_lord": "Sun", "star_lord": "Ketu", "sub_lord": "Sun", "sub_sub_lord": "Rahu"}], "asc_sign_index": 5, "significators": {"Sun": {"owns": [12], "occupies": 9, "star_lord_owns": [12], "signifies": [9, 12]}, "Moon": {"owns": [11], "occupies": 5, "star_lord_owns": [12], "signifies": [5, 11, 12]}, "Mars": {"owns": [3, 8], "occupies": 6, "star_lord_owns": [4, 7], "signifies": [3, 4, 6, 7, 8]}, "Mercury": {"owns": [1, 10], "occupies": 8, "star_lord_owns": [2, 9], "signifies": [1, 2, 8, 9, 10]}, "Jupiter": {"owns": [4, 7], "occupies": 10, "star_lord_owns": [], "signifies": [4, 7, 10]}, "Venus": {"owns": [2, 9], "occupies": 7, "star_lord_owns": [1, 10], "signifies": [1, 2, 7, 9, 10]}, "Saturn": {"owns": [5, 6], "occupies": 5, "star_lord_owns": [12], "signifies": [5, 6, 12]}, "Rahu": {"owns": [], "occupies": 5, "star_lord_owns": [11], "signifies": [5, 11]}, "Ketu": {"owns": [], "occupies": 11, "star_lord_owns": [1, 10], "signifies": [1, 10, 11]}}, "promise": {"1": {"cusp_sub_lord": "Jupiter", "sub_lord_signifies": [4, 7, 10], "promise": "mixed"}, "2": {"cusp_sub_lord": "Ketu", "sub_lord_signifies": [11], "promise": "mixed"}, "3": {"cusp_sub_lord": "Rahu", "sub_lord_signifies": [5], "promise": "mixed"}, "4": {"cusp_sub_lord": "Venus", "sub_lord_signifies": [2, 7, 9], "promise": "mixed"}, "5": {"cusp_sub_lord": "Jupiter", "sub_lord_signifies": [4, 7, 10], "promise": "mixed"}, "6": {"cusp_sub_lord": "Venus", "sub_lord_signifies": [2, 7, 9], "promise": "mixed"}, "7": {"cusp_sub_lord": "Rahu", "sub_lord_signifies": [5], "promise": "mixed"}, "8": {"cusp_sub_lord": "Venus", "sub_lord_signifies": [2, 7, 9], "promise": "mixed"}, "9": {"cusp_sub_lord": "Jupiter", "sub_lord_signifies": [4, 7, 10], "promise": "mixed"}, "10": {"cusp_sub_lord": "Venus", "sub_lord_signifies": [2, 7, 9], "promise": "mixed"}, "11": {"cusp_sub_lord": "Rahu", "sub_lord_signifies": [5], "promise": "mixed"}, "12": {"cusp_sub_lord": "Sun", "sub_lord_signifies": [9, 12], "promise": "strong"}}, "cuspal_interlinks": {"marriage": {"required_houses": [2, 7, 11], "cusp_sub_lords": {"2": "Ketu", "7": "Rahu", "11": "Rahu"}}, "employment": {"required_houses": [2, 6, 10, 11], "cusp_sub_lords": {"2": "Ketu", "6": "Venus", "10": "Venus", "11": "Rahu"}}, "foreign": {"required_houses": [3, 9, 12], "cusp_sub_lords": {"3": "Rahu", "9": "Jupiter", "12": "Sun"}}, "property": {"required_houses": [4, 11, 12], "cusp_sub_lords": {"4": "Venus", "11": "Rahu", "12": "Sun"}}, "children": {"required_houses": [2, 5, 11], "cusp_sub_lords": {"2": "Ketu", "5": "Jupiter", "11": "Rahu"}}, "health_recovery": {"required_houses": [1, 5, 11], "cusp_sub_lords": {"1": "Jupiter", "5": "Jupiter", "11": "Rahu"}}, "business": {"required_houses": [2, 7, 10, 11], "cusp_sub_lords": {"2": "Ketu", "7": "Rahu", "10": "Venus", "11": "Rahu"}}}}, "bazi": {"pillars": {"year": {"stem": "Geng", "stem_element": "Metal", "stem_polarity": "Yang", "branch": "Wu", "animal": "Horse", "branch_element": "Fire", "hidden_stems": ["Ding", "Ji"]}, "month": {"stem": "Xin", "stem_element": "Metal", "stem_polarity": "Yin", "branch": "Si", "animal": "Snake", "branch_element": "Fire", "hidden_stems": ["Bing", "Wu", "Geng"]}, "day": {"stem": "Geng", "stem_element": "Metal", "stem_polarity": "Yang", "branch": "Chen", "animal": "Dragon", "branch_element": "Earth", "hidden_stems": ["Wu", "Yi", "Gui"]}, "hour": {"stem": "Gui", "stem_element": "Water", "stem_polarity": "Yin", "branch": "Wei", "animal": "Goat", "branch_element": "Earth", "hidden_stems": ["Ji", "Ding", "Yi"]}, "day_master": "Geng", "day_master_element": "Metal", "day_master_polarity": "Yang", "bazi_year": 1990, "_idx": {"year_stem": 6, "year_branch": 6, "month_branch": 5, "day_stem": 6, "day_branch": 4, "hour_branch": 7}}, "day_master_analysis": {"day_master_element": "Metal", "day_master_polarity": "Yang", "strength": "Strong", "seasonal_strength_score": 2, "season_supports": false, "favourable_elements": ["Fire", "Wood"], "unfavourable_elements": ["Earth", "Metal"], "dominant_element": "Metal", "missing_element": "Wood", "element_counts": {"Wood": 0, "Fire": 2, "Earth": 2, "Metal": 3, "Water": 1}}, "ten_gods": {"year_stem": "Friend (BJ)", "month_stem": "Rob Wealth (JC)", "hour_stem": "Hurting Officer (SC)"}, "luck_pillars": {"direction": "forward", "start_age": 7.2, "pillars": [{"from_age": 7.2, "to_age": 17.2, "stem": "Ren", "stem_element": "Water", "branch": "Wu", "animal": "Horse", "branch_element": "Fire"}, {"from_age": 17.2, "to_age": 27.2, "stem": "Gui", "stem_element": "Water", "branch": "Wei", "animal": "Goat", "branch_element": "Earth"}, {"from_age": 27.2, "to_age": 37.2, "stem": "Jia", "stem_element": "Wood", "branch": "Shen", "animal": "Monkey", "branch_element": "Metal"}, {"from_age": 37.2, "to_age": 47.2, "stem": "Yi", "stem_element": "Wood", "branch": "You", "animal": "Rooster", "branch_element": "Metal"}, {"from_age": 47.2, "to_age": 57.2, "stem": "Bing", "stem_element": "Fire", "branch": "Xu", "animal": "Dog", "branch_element": "Earth"}, {"from_age": 57.2, "to_age": 67.2, "stem": "Ding", "stem_element": "Fire", "branch": "Hai", "animal": "Pig", "branch_element": "Water"}, {"from_age": 67.2, "to_age": 77.2, "stem": "Wu", "stem_element": "Earth", "branch": "Zi", "animal": "Rat", "branch_element": "Water"}, {"from_age": 77.2, "to_age": 87.2, "stem": "Ji", "stem_element": "Earth", "branch": "Chou", "animal": "Ox", "branch_element": "Earth"}, {"from_age": 87.2, "to_age": 97.2, "stem": "Geng", "stem_element": "Metal", "branch": "Yin", "animal": "Tiger", "branch_element": "Wood"}]}, "branch_interactions": {"clashes": [], "combinations": ["Wu-Wei \u2192 Earth"], "harms": [], "destructions": [], "three_harmony": [], "dual_nature_resolution": []}, "shen_sha": {"active": ["Nobleman (Tian Yi Gui Ren)"]}, "kong_wang": {"void_branches": ["Zi", "Chou"]}, "hour_known": true}, "ziwei": {"available": true, "wu_xing_ju": "Earth Bureau 5", "bureau_element": "Earth", "bureau_number": 5, "life_palace": {"palace": "Ming Gong", "domain": "Life", "branch": "Xu", "stars": ["Zi Wei", "Tian Xiang"]}, "body_palace": "Zi", "body_palace_name": "Fu De", "palaces": {"Ming Gong": {"branch": "Xu", "animal": "Dog", "domain": "Life", "branch_index": 10, "stars": ["Zi Wei", "Tian Xiang"]}, "Xiong Di": {"branch": "You", "animal": "Rooster", "domain": "Siblings", "branch_index": 9, "stars": ["Tian Ji", "Ju Men"]}, "Fu Qi": {"branch": "Shen", "animal": "Monkey", "domain": "Spouse", "branch_index": 8, "stars": ["Tan Lang"]}, "Zi Nu": {"branch": "Wei", "animal": "Goat", "domain": "Children", "branch_index": 7, "stars": ["Tai Yang", "Tai Yin"]}, "Cai Bo": {"branch": "Wu", "animal": "Horse", "domain": "Wealth", "branch_index": 6, "stars": ["Wu Qu", "Tian Fu"]}, "Ji E": {"branch": "Si", "animal": "Snake", "domain": "Health", "branch_index": 5, "stars": ["Tian Tong"]}, "Qian Yi": {"branch": "Chen", "animal": "Dragon", "domain": "Travel", "branch_index": 4, "stars": ["Po Jun"]}, "Jiao You": {"branch": "Mao", "animal": "Rabbit", "domain": "Friends", "branch_index": 3, "stars": []}, "Guan Lu": {"branch": "Yin", "animal": "Tiger", "domain": "Career", "branch_index": 2, "stars": ["Lian Zhen"]}, "Tian Zhai": {"branch": "Chou", "animal": "Ox", "domain": "Property", "branch_index": 1, "stars": []}, "Fu De": {"branch": "Zi", "animal": "Rat", "domain": "Karma", "branch_index": 0, "stars": ["Qi Sha"]}, "Fu Mu": {"branch": "Hai", "animal": "Pig", "domain": "Parents", "branch_index": 11, "stars": ["Tian Liang"]}}, "hua_transformations": {"Lu": "Tai Yang", "Quan": "Wu Qu", "Ke": "Tai Yin", "Ji": "Tian Tong"}, "san_fang_si_zheng": {"Life group": ["Ming Gong", "Guan Lu", "Cai Bo", "Qian Yi"], "Spouse group": ["Fu Qi", "Zi Nu", "Tian Zhai", "Fu De"], "Siblings group": ["Xiong Di", "Jiao You", "Fu Mu", "Ji E"]}, "opposition_pairs": {"Ming Gong": "Qian Yi", "Guan Lu": "Cai Bo", "Fu Qi": "Fu De", "Ji E": "Jiao You", "Tian Zhai": "Xiong Di", "Zi Nu": "Fu Mu"}, "da_xian": {"direction": "forward", "periods": [{"from_age": 5, "to_age": 14, "palace": "Ming Gong", "stars": ["Zi Wei", "Tian Xiang"], "flying_stars": {"Lu": "Tian Tong", "Quan": "Tian Ji", "Ke": "Wen Chang", "Ji": "Lian Zhen"}}, {"from_age": 15, "to_age": 24, "palace": "Fu Mu", "stars": ["Tian Liang"], "flying_stars": {"Lu": "Tai Yin", "Quan": "Tian Tong", "Ke": "Tian Ji", "Ji": "Ju Men"}}, {"from_age": 25, "to_age": 34, "palace": "Fu De", "stars": ["Qi Sha"], "flying_stars": {"Lu": "Tian Tong", "Quan": "Tian Ji", "Ke": "Wen Chang", "Ji": "Lian Zhen"}}, {"from_age": 35, "to_age": 44, "palace": "Tian Zhai", "stars": [], "flying_stars": {"Lu": "Tai Yin", "Quan": "Tian Tong", "Ke": "Tian Ji", "Ji": "Ju Men"}}, {"from_age": 45, "to_age": 54, "palace": "Guan Lu", "stars": ["Lian Zhen"], "flying_stars": {"Lu": "Tan Lang", "Quan": "Tai Yin", "Ke": "You Bi", "Ji": "Tian Ji"}}, {"from_age": 55, "to_age": 64, "palace": "Jiao You", "stars": [], "flying_stars": {"Lu": "Wu Qu", "Quan": "Tan Lang", "Ke": "Tian Liang", "Ji": "Wen Qu"}}, {"from_age": 65, "to_age": 74, "palace": "Qian Yi", "stars": ["Po Jun"], "flying_stars": {"Lu": "Tai Yang", "Quan": "Wu Qu", "Ke": "Tai Yin", "Ji": "Tian Tong"}}, {"from_age": 75, "to_age": 84, "palace": "Ji E", "stars": ["Tian Tong"], "flying_stars": {"Lu": "Ju Men", "Quan": "Tai Yang", "Ke": "Wen Qu", "Ji": "Wen Chang"}}, {"from_age": 85, "to_age": 94, "palace": "Cai Bo", "stars": ["Wu Qu", "Tian Fu"], "flying_stars": {"Lu": "Tian Liang", "Quan": "Zi Wei", "Ke": "Zuo Fu", "Ji": "Wu Qu"}}]}, "annual_palaces": {"2020": "Fu De", "2021": "Tian Zhai", "2022": "Guan Lu", "2023": "Jiao You", "2024": "Qian Yi", "2025": "Ji E", "2026": "Cai Bo", "2027": "Zi Nu", "2028": "Fu Qi", "2029": "Xiong Di", "2030": "Ming Gong", "2031": "Fu Mu", "2032": "Fu De", "2033": "Tian Zhai", "2034": "Guan Lu", "2035": "Jiao You"}}, "cache_keys": {"vedic_yoga_strings": ["Malavya Yoga (Mahapurusha) strong", "Amala Yoga medium", "Vipreet Raja Yoga (Sarala) medium", "Dhana Yoga medium"], "parivartana_cache": [], "active_period_snapshot": {"vedic_dasha": "Rahu-Sun", "bazi_luck_pillar": "Jia/Wood (Monkey/Metal)", "ziwei_da_xian": "Ming Gong"}, "dominant_bazi_element": "Metal_Strong", "elemental_imbalance_flag": "Deficient_Wood", "ashtakavarga_matrix": [26, 23, 30, 25, 25, 27, 24, 38, 29, 27, 32, 31], "core_temperament_style": "Disciplined_Achiever", "life_phase_classification": "Transition Phase (change and release)", "sade_sati": {"active": false, "phase": null}, "favourable_elements": ["Fire", "Wood"], "unfavourable_elements": ["Earth", "Metal"], "bazi_interaction_map": ["combination: Wu-Wei \u2192 Earth", "ten-gods: year=Friend (BJ), month=Rob Wealth (JC), hour=Hurting Officer (SC)"]}}